refstr.py
refstr-1.0.dist-info/LICENSE
refstr-1.0.dist-info/METADATA
refstr-1.0.dist-info/WHEEL
refstr-1.0.dist-info/top_level.txt
refstr-1.0.dist-info/RECORD
