Metadata-Version: 2.1
Name: refstr
Version: 1.0
Summary: Referenceable String
Home-page: https://github.com/EcmaXp/refstr
Author: EcmaXp
Author-email: ecmaxp+refstr@ecmaxp.pe.kr
License: UNKNOWN
Keywords: typing,reference,string
Platform: UNKNOWN
Classifier: Development Status :: 5 - Production/Stable
Classifier: Intended Audience :: Developers
Classifier: License :: OSI Approved :: The Unlicense (Unlicense)
Classifier: Operating System :: OS Independent
Classifier: Programming Language :: Python :: 2.7
Classifier: Programming Language :: Python :: 3
Classifier: Topic :: Software Development
Requires-Python: >=2.7, >=3
